biokinepy/__init__.py
biokinepy/absor.py
biokinepy/cs.py
biokinepy/euler_angles.py
biokinepy/filling.py
biokinepy/joint_center.py
biokinepy/mean_smoother.py
biokinepy/np_utils.py
biokinepy/segment_cs.py
biokinepy/trajectory.py
biokinepy/vec_ops.py
biokinepy/vel_acc.py
biokinepy-0.1.2.dist-info/LICENSE.txt
biokinepy-0.1.2.dist-info/METADATA
biokinepy-0.1.2.dist-info/WHEEL
biokinepy-0.1.2.dist-info/top_level.txt
biokinepy-0.1.2.dist-info/RECORD
