Metadata-Version: 2.1
Name: biokinepy
Version: 0.1.2
Summary: Utilities for processing, computing, and analyzing joint kinematics.
Home-page: https://github.com/klevis-a/biokinepy
Author: Klevis Aliaj
Author-email: klevis.a@gmail.com
License: MIT
Keywords: biomechanics,kinematics,kinematic analysis,motion capture,skin marker,quaternion,homogeneous transformation,angular velocity
Platform: UNKNOWN
Classifier: License :: OSI Approved :: MIT License
Classifier: Programming Language :: Python :: 3
Classifier: Programming Language :: Python :: 3.7
Requires-Python: >=3.7
Requires-Dist: numpy
Requires-Dist: numpy-quaternion
Requires-Dist: scipy
Requires-Dist: lazy
